LICENSE
MANIFEST.in
README.rst
setup.py
django_servee_image.egg-info/PKG-INFO
django_servee_image.egg-info/SOURCES.txt
django_servee_image.egg-info/dependency_links.txt
django_servee_image.egg-info/not-zip-safe
django_servee_image.egg-info/requires.txt
django_servee_image.egg-info/top_level.txt
servee_image/__init__.py
servee_image/admin.py
servee_image/models.py
servee_image/servee_registry.py
servee_image/settings.py
servee_image/templates/servee/wysiwyg/insert/servee_image/_add.html
servee_image/templates/servee/wysiwyg/insert/servee_image/_detail.html
servee_image/templates/servee/wysiwyg/insert/servee_image/_list.html
servee_image/templates/servee/wysiwyg/insert/servee_image/_render.html